pomodoro/__init__.py
pomodoro/const.py
pomodoro/pomodoro.py
pomodoro/util.py
pomodoro/data/icons/README.md
pomodoro/data/icons/check.png
pomodoro/data/icons/exit.png
pomodoro/data/icons/statistics.png
pomodoro/data/icons/tasks.png
pomodoro/data/icons/timer.png
pomodoro/data/icons/tomato.ico
pomodoro/data/icons/tomato.png
pomodoro/data/icons/trash.png
pomodoro_gui-0.0.7.dist-info/LICENSE
pomodoro_gui-0.0.7.dist-info/METADATA
pomodoro_gui-0.0.7.dist-info/WHEEL
pomodoro_gui-0.0.7.dist-info/entry_points.txt
pomodoro_gui-0.0.7.dist-info/top_level.txt
pomodoro_gui-0.0.7.dist-info/RECORD
