Metadata-Version: 2.1
Name: pomodoro-gui
Version: 0.0.7
Summary: A small pomodoro GUI for Windows/Linux created with PyQt5.
Home-page: https://github.com/burakmartin/pomodoro
Author: Burak Martin
Author-email: burak.martin100@gmail.com
License: GPL-3.0-or-later
Platform: UNKNOWN
Classifier: Programming Language :: Python :: 3
Classifier: License :: OSI Approved :: GNU General Public License v3 (GPLv3)
Classifier: Operating System :: OS Independent
Requires-Python: >=3.5
Requires-Dist: PyQt5 (>=5.15.0)
Requires-Dist: QDarkStyle (>=2.8.1)
